{
    "legends": [
        {
            "autor_name": null, 
            "autor_rank": null, 
            "cd": "1CD", 
            "comments": "0", 
            "date": "13/09/2013", 
            "downloads": 746, 
            "fps": 24.0, 
            "imdbVote": "7.8", 
            "language": "Portugu\u00eas-BR", 
            "link_download": "http://www.opensubtitles.org/pb/subtitleserve/sub/5174895", 
            "name_movie": "Man som hatar kvinnor (2009)", 
            "name_movie_file": "The.Girl.With.The.Dragon.Tattoo.2009.Extended.x264.DTS-WAF", 
            "punctuation": "0.0", 
            "quality_legend": []
        }, 
        {
            "autor_name": "lincolnh_sp", 
            "autor_rank": null, 
            "cd": "1CD", 
            "comments": "0", 
            "date": "14/08/2013", 
            "downloads": 508, 
            "fps": 23.976, 
            "imdbVote": "7.8", 
            "language": "Portugu\u00eas-BR", 
            "link_download": "http://www.opensubtitles.org/pb/subtitleserve/sub/5133459", 
            "name_movie": "Man som hatar kvinnor (2009)", 
            "name_movie_file": "M\u00e4n.som.hatar.kvinnor.2009.720p.BluRay-x264-NODLABS", 
            "punctuation": "0.0", 
            "quality_legend": [
                "hd"
            ]
        }, 
        {
            "autor_name": "CharlesChaplinJr", 
            "autor_rank": "trusted", 
            "cd": "1CD", 
            "comments": "0", 
            "date": "12/06/2012", 
            "downloads": 795, 
            "fps": 0.0, 
            "imdbVote": "7.8", 
            "language": "Portugu\u00eas-BR", 
            "link_download": "http://www.opensubtitles.org/pb/subtitleserve/sub/4574897", 
            "name_movie": "Man som hatar kvinnor (2009)", 
            "name_movie_file": "        ", 
            "punctuation": "0.0", 
            "quality_legend": [
                "from_trusted"
            ]
        }, 
        {
            "autor_name": null, 
            "autor_rank": null, 
            "cd": "2CD", 
            "comments": "0", 
            "date": "04/06/2012", 
            "downloads": 580, 
            "fps": 25.0, 
            "imdbVote": "7.8", 
            "language": "Portugu\u00eas-BR", 
            "link_download": "http://www.opensubtitles.org/pb/subtitleserve/sub/4569299", 
            "name_movie": "Man som hatar kvinnor (2009)", 
            "name_movie_file": "Flickan.Som.Lekte.Med.Elden.2009.SWEDiSH.DVDRip.XviD-Skvaguratet.CD01", 
            "punctuation": "0.0", 
            "quality_legend": []
        }, 
        {
            "autor_name": null, 
            "autor_rank": null, 
            "cd": "1CD", 
            "comments": "0", 
            "date": "30/09/2011", 
            "downloads": 1517, 
            "fps": 23.976, 
            "imdbVote": "7.8", 
            "language": "Portugu\u00eas-BR", 
            "link_download": "http://www.opensubtitles.org/pb/subtitleserve/sub/4246387", 
            "name_movie": "Man som hatar kvinnor (2009)", 
            "name_movie_file": "Millennium 1 - Os Homens Que Odeiam As Mulheres cd2", 
            "punctuation": "0.0", 
            "quality_legend": []
        }, 
        {
            "autor_name": "flatlightning", 
            "autor_rank": null, 
            "cd": "1CD", 
            "comments": "0", 
            "date": "13/02/2011", 
            "downloads": 4157, 
            "fps": 0.0, 
            "imdbVote": "7.8", 
            "language": "Portuguese (BR)", 
            "link_download": "http://www.opensubtitles.org/pb/subtitleserve/sub/4095634", 
            "name_movie": "Man som hatar kvinnor (2009)", 
            "name_movie_file": "The.Girl.with.the.Dragon.Tattoo.2009.720p.BluRay-x264-NODLABS", 
            "punctuation": "0.0", 
            "quality_legend": [
                "hd"
            ]
        }, 
        {
            "autor_name": null, 
            "autor_rank": null, 
            "cd": "1CD", 
            "comments": "0", 
            "date": "24/01/2011", 
            "downloads": 943, 
            "fps": 25.0, 
            "imdbVote": "7.8", 
            "language": "Portugu\u00eas-BR", 
            "link_download": "http://www.opensubtitles.org/pb/subtitleserve/sub/4066695", 
            "name_movie": "Man som hatar kvinnor (2009)", 
            "name_movie_file": "        ", 
            "punctuation": "0.0", 
            "quality_legend": []
        }, 
        {
            "autor_name": null, 
            "autor_rank": null, 
            "cd": "1CD", 
            "comments": "0", 
            "date": "19/12/2010", 
            "downloads": 630, 
            "fps": 0.0, 
            "imdbVote": "7.8", 
            "language": "Portugu\u00eas-BR", 
            "link_download": "http://www.opensubtitles.org/pb/subtitleserve/sub/4014072", 
            "name_movie": "Man som hatar kvinnor (2009)", 
            "name_movie_file": "        ", 
            "punctuation": "0.0", 
            "quality_legend": []
        }, 
        {
            "autor_name": null, 
            "autor_rank": null, 
            "cd": "1CD", 
            "comments": "0", 
            "date": "12/11/2010", 
            "downloads": 1279, 
            "fps": 24.0, 
            "imdbVote": "7.8", 
            "language": "Portugu\u00eas-BR", 
            "link_download": "http://www.opensubtitles.org/pb/subtitleserve/sub/3950663", 
            "name_movie": "Man som hatar kvinnor (2009)", 
            "name_movie_file": "Man.Som.Hatar.Kvinnor.(2009).DVDRip.AC3.XviD-WHiiZz.[sharethefiles.com]", 
            "punctuation": "0.0", 
            "quality_legend": []
        }, 
        {
            "autor_name": null, 
            "autor_rank": null, 
            "cd": "2CD", 
            "comments": "0", 
            "date": "27/10/2010", 
            "downloads": 941, 
            "fps": 25.0, 
            "imdbVote": "7.8", 
            "language": "Portuguese (BR)", 
            "link_download": "http://www.opensubtitles.org/pb/subtitleserve/sub/3917035", 
            "name_movie": "Man som hatar kvinnor (2009)", 
            "name_movie_file": "        ", 
            "punctuation": "0.0", 
            "quality_legend": []
        }, 
        {
            "autor_name": null, 
            "autor_rank": null, 
            "cd": "1CD", 
            "comments": "0", 
            "date": "27/09/2010", 
            "downloads": 2283, 
            "fps": 23.976, 
            "imdbVote": "7.8", 
            "language": "Portugu\u00eas-BR", 
            "link_download": "http://www.opensubtitles.org/pb/subtitleserve/sub/3851532", 
            "name_movie": "Man som hatar kvinnor (2009)", 
            "name_movie_file": "        ", 
            "punctuation": "0.0", 
            "quality_legend": []
        }, 
        {
            "autor_name": null, 
            "autor_rank": null, 
            "cd": "2CD", 
            "comments": "0", 
            "date": "29/08/2010", 
            "downloads": 1066, 
            "fps": 23.976, 
            "imdbVote": "7.8", 
            "language": "Portuguese (BR)", 
            "link_download": "http://www.opensubtitles.org/pb/subtitleserve/sub/3788816", 
            "name_movie": "Man som hatar kvinnor (2009)", 
            "name_movie_file": "The.Girl.with.the.Dragon.Tattoo.2009.LiMiTED.PROPER.DVDRip.XviD-NODLABS", 
            "punctuation": "0.0", 
            "quality_legend": []
        }, 
        {
            "autor_name": "cinefala", 
            "autor_rank": "trusted", 
            "cd": "1CD", 
            "comments": "0", 
            "date": "27/08/2010", 
            "downloads": 1055, 
            "fps": 29.97, 
            "imdbVote": "7.8", 
            "language": "Portugu\u00eas-BR", 
            "link_download": "http://www.opensubtitles.org/pb/subtitleserve/sub/3783551", 
            "name_movie": "Man som hatar kvinnor (2009)", 
            "name_movie_file": "Os.Homens.Que.Nao.Amavam.as.Mulheres.Dual.ptbr.Sv.DvdRip.Xvid.Ac3.Brazilinjapan.by.cinefila.avi", 
            "punctuation": "0.0", 
            "quality_legend": [
                "from_trusted"
            ]
        }, 
        {
            "autor_name": "tucanalha", 
            "autor_rank": "trusted", 
            "cd": "2CD", 
            "comments": "0", 
            "date": "16/06/2010", 
            "downloads": 2554, 
            "fps": 29.97, 
            "imdbVote": "7.8", 
            "language": "Portuguese (BR)", 
            "link_download": "http://www.opensubtitles.org/pb/subtitleserve/sub/3689941", 
            "name_movie": "Man som hatar kvinnor (2009)", 
            "name_movie_file": "        ", 
            "punctuation": "0.0", 
            "quality_legend": [
                "from_trusted"
            ]
        }, 
        {
            "autor_name": "jqa", 
            "autor_rank": null, 
            "cd": "1CD", 
            "comments": "0", 
            "date": "19/02/2010", 
            "downloads": 2866, 
            "fps": 23.976, 
            "imdbVote": "7.8", 
            "language": "Portuguese (BR)", 
            "link_download": "http://www.opensubtitles.org/pb/subtitleserve/sub/3642861", 
            "name_movie": "Man som hatar kvinnor (2009)", 
            "name_movie_file": "        ", 
            "punctuation": "0.0", 
            "quality_legend": [
                "hd"
            ]
        }, 
        {
            "autor_name": null, 
            "autor_rank": null, 
            "cd": "1CD", 
            "comments": "0", 
            "date": "17/12/2009", 
            "downloads": 2379, 
            "fps": 24.0, 
            "imdbVote": "7.8", 
            "language": "Portuguese (BR)", 
            "link_download": "http://www.opensubtitles.org/pb/subtitleserve/sub/3609587", 
            "name_movie": "Man som hatar kvinnor (2009)", 
            "name_movie_file": "Man.Som.Hatar.Kvinnor.2009.720p.BluRay.DTS.x264-ESiR", 
            "punctuation": "0.0", 
            "quality_legend": [
                "hd"
            ]
        }, 
        {
            "autor_name": "gutoresquin", 
            "autor_rank": "administrator", 
            "cd": "1CD", 
            "comments": "0", 
            "date": "19/11/2009", 
            "downloads": 6048, 
            "fps": 23.976, 
            "imdbVote": "7.8", 
            "language": "Portuguese (BR)", 
            "link_download": "http://www.opensubtitles.org/pb/subtitleserve/sub/3594498", 
            "name_movie": "Man som hatar kvinnor (2009)", 
            "name_movie_file": "The.Girl.with.the.Dragon.Tattoo.2009.DVDRip.XviD-LAP", 
            "punctuation": "0.0", 
            "quality_legend": [
                "from_trusted"
            ]
        }, 
        {
            "autor_name": "gutoresquin", 
            "autor_rank": "administrator", 
            "cd": "2CD", 
            "comments": "0", 
            "date": "19/11/2009", 
            "downloads": 1365, 
            "fps": 23.976, 
            "imdbVote": "7.8", 
            "language": "Portugu\u00eas-BR", 
            "link_download": "http://www.opensubtitles.org/pb/subtitleserve/sub/3594497", 
            "name_movie": "Man som hatar kvinnor (2009)", 
            "name_movie_file": "The.Girl.with.the.Dragon.Tattoo.2009.DVDRip.XviD-LAP", 
            "punctuation": "0.0", 
            "quality_legend": [
                "from_trusted"
            ]
        }, 
        {
            "autor_name": "leonardoborges", 
            "autor_rank": "gold member", 
            "cd": "2CD", 
            "comments": "0", 
            "date": "23/09/2009", 
            "downloads": 1279, 
            "fps": 25.0, 
            "imdbVote": "7.8", 
            "language": "Portugu\u00eas-BR", 
            "link_download": "http://www.opensubtitles.org/pb/subtitleserve/sub/3564741", 
            "name_movie": "Man som hatar kvinnor (2009)", 
            "name_movie_file": "        ", 
            "punctuation": "0.0", 
            "quality_legend": []
        }, 
        {
            "autor_name": "noriegaRJ", 
            "autor_rank": "administrator", 
            "cd": "2CD", 
            "comments": "0", 
            "date": "01/09/2009", 
            "downloads": 2254, 
            "fps": 30.0, 
            "imdbVote": "7.8", 
            "language": "Portugu\u00eas-BR", 
            "link_download": "http://www.opensubtitles.org/pb/subtitleserve/sub/3554848", 
            "name_movie": "Man som hatar kvinnor (2009)", 
            "name_movie_file": "        ", 
            "punctuation": "0.0", 
            "quality_legend": [
                "from_trusted"
            ]
        }, 
        {
            "autor_name": "noriegaRJ", 
            "autor_rank": "administrator", 
            "cd": "2CD", 
            "comments": "0", 
            "date": "01/09/2009", 
            "downloads": 3666, 
            "fps": 25.0, 
            "imdbVote": "7.8", 
            "language": "Portuguese (BR)", 
            "link_download": "http://www.opensubtitles.org/pb/subtitleserve/sub/3554846", 
            "name_movie": "Man som hatar kvinnor (2009)", 
            "name_movie_file": "Man.Som.Hatar.Kvinnor.2009.SWEDISH.DVDRip.XviD-Sabelma", 
            "punctuation": "0.0", 
            "quality_legend": [
                "from_trusted"
            ]
        }
    ], 
    "response": true
}
